setup.py
WebtrendsQT/__init__.py
WebtrendsQT/wtqt.py
WebtrendsQT.egg-info/PKG-INFO
WebtrendsQT.egg-info/SOURCES.txt
WebtrendsQT.egg-info/dependency_links.txt
WebtrendsQT.egg-info/entry_points.txt
WebtrendsQT.egg-info/top_level.txt