Metadata-Version: 1.0
Name: WebtrendsQT
Version: 0.1
Summary: Webtrends SQL query tool
Home-page: http://github.com/isotoma/WebtrendsQT
Author: Wes Mason
Author-email: wes.mason@isotoma.com
License: Apache License 2.0
Platform: Windows
